odoo/addons/account_cash_invoice/README.rst
odoo/addons/account_cash_invoice/__init__.py
odoo/addons/account_cash_invoice/__manifest__.py
odoo/addons/account_cash_invoice/models/__init__.py
odoo/addons/account_cash_invoice/models/account_bank_statement_line.py
odoo/addons/account_cash_invoice/static/description/icon.png
odoo/addons/account_cash_invoice/tests/__init__.py
odoo/addons/account_cash_invoice/tests/test_pay_invoice.py
odoo/addons/account_cash_invoice/wizard/__init__.py
odoo/addons/account_cash_invoice/wizard/cash_invoice_in.py
odoo/addons/account_cash_invoice/wizard/cash_invoice_in.xml
odoo/addons/account_cash_invoice/wizard/cash_invoice_out.py
odoo/addons/account_cash_invoice/wizard/cash_invoice_out.xml
odoo11_addon_account_cash_invoice-11.0.1.1.0.dist-info/DESCRIPTION.rst
odoo11_addon_account_cash_invoice-11.0.1.1.0.dist-info/METADATA
odoo11_addon_account_cash_invoice-11.0.1.1.0.dist-info/RECORD
odoo11_addon_account_cash_invoice-11.0.1.1.0.dist-info/WHEEL
odoo11_addon_account_cash_invoice-11.0.1.1.0.dist-info/metadata.json
odoo11_addon_account_cash_invoice-11.0.1.1.0.dist-info/top_level.txt
